grismconf/__init__.py
grismconf/grismconf.py
grismconf/poly.py
grismconf/specwcs.py
grismconf-1.51.dist-info/METADATA
grismconf-1.51.dist-info/SOURCES (Nor Pirzkal's conflicted copy 2024-01-05 1).txt
grismconf-1.51.dist-info/SOURCES (Nor Pirzkal's conflicted copy 2024-01-05).txt
grismconf-1.51.dist-info/WHEEL
grismconf-1.51.dist-info/top_level.txt
grismconf-1.51.dist-info/RECORD
