Metadata-Version: 2.1
Name: grismconf
Version: 1.51
Summary: GRISM Configuration python code, described in ISR 2017-01: A More Generalized Coordinate Transformation Approach for Grisms, Pirzkal & Ryan 2017 http://www.stsci.edu/hst/wfc3/documents/ISRs/WFC3-2017-01.pdf
Home-page: https://github.com/npirzkal/GRISMCONF
Author: Nor Pirzkal
Author-email: npirzkal@mac.com
